Tutorials/src/tempmux.vhd
entity tempmux is
    port ( CURRENT_TEMP     : in bit_vector(6 downto 0);
           DESIRED_TEMP     : in bit_vector(6 downto 0);
           DISPLAY_SELECT   : in bit;
           COOL             : in bit;
           HEAT             : in bit;
           A_C_ON           : out bit;
           FURNACE_ON       : out bit;
           TEMP_DISPLAY     : out bit_vector(6 downto 0)
    );
end tempmux;

architecture RTL of tempmux is
    begin
        DISPLAY: process(DISPLAY_SELECT, CURRENT_TEMP, DESIRED_TEMP)
        begin
            if DISPLAY_SELECT = '1' then
                TEMP_DISPLAY <= CURRENT_TEMP;
            else
                TEMP_DISPLAY <= DESIRED_TEMP;
            end if;
        end process;

        THERMOSTAT: process(COOL, HEAT, DESIRED_TEMP)
        begin
            if COOL = '1' and CURRENT_TEMP > DESIRED_TEMP then
                A_C_ON <= '1';
            elsif HEAT = '1' and CURRENT_TEMP < DESIRED_TEMP then
                FURNACE_ON <= '1';
            else
                A_C_ON <= '0';
                FURNACE_ON <= '0';
            end if;
        end process;
    end RTL;

Tutorials/src/tempmux_tb.vhd
entity tempmux_tb is 
    
end tempmux_tb;

architecture TEST of tempmux_tb is
component tempmux
    port ( CURRENT_TEMP     : in bit_vector(6 downto 0);
           DESIRED_TEMP     : in bit_vector(6 downto 0);
           DISPLAY_SELECT   : in bit;
           COOL             : in bit;
           HEAT             : in bit;
           A_C_ON           : out bit;
           FURNACE_ON       : out bit;
           TEMP_DISPLAY     : out bit_vector(6 downto 0)
         );
end component;

signal CURRENT_TEMP, DESIRED_TEMP : bit_vector (6 downto 0);
signal TEMP_DISPLAY : bit_vector (6 downto 0);
signal A_C_ON : bit;
signal FURNACE_ON : bit;
signal DISPLAY_SELECT : bit;
signal COOL : bit;
signal HEAT : bit;

begin
    UUT: entity work.tempmux(RTL) port map (
                            CURRENT_TEMP => CURRENT_TEMP,
                            DESIRED_TEMP => DESIRED_TEMP,
                            DISPLAY_SELECT => DISPLAY_SELECT,
                            COOL => COOL,
                            HEAT => HEAT,
                            A_C_ON => A_C_ON,
                            FURNACE_ON => FURNACE_ON,
                            TEMP_DISPLAY => TEMP_DISPLAY);
    
    process
    begin
        CURRENT_TEMP <= "0000000";
        DESIRED_TEMP <= "1111111";
        DISPLAY_SELECT <= '0';
        wait for 10 ns;
        DISPLAY_SELECT <= '1';
        wait for 10 ns;
        HEAT <= '1';
        COOL <= '0';
        wait for 10 ns;

        CURRENT_TEMP <= "1111111";
        DESIRED_TEMP <= "0000000";
        wait for 10 ns;
        COOL <= '1';
        HEAT <= '0';
        wait for 10 ns;

        CURRENT_TEMP <= "1111111";
        DESIRED_TEMP <= "0000000";
        wait for 10 ns;
        COOL <= '0';
        HEAT <= '1';
        wait for 10 ns;

        CURRENT_TEMP <= "0000000";
        DESIRED_TEMP <= "1111111";
        wait for 10 ns;
        COOL <= '1';
        HEAT <= '0';
        wait for 10 ns;
        wait;
    end process;
end;

Tutorials/src/work/tempmux_tb.vcd
$date
  Sun Oct 24 22:38:21 2021
$end
$version
  GHDL v0
$end
$timescale
  1 fs
$end
$scope module standard $end
$upscope $end
$scope module tempmux_tb $end
$var reg 7 ! current_temp[6:0] $end
$var reg 7 " desired_temp[6:0] $end
$var reg 7 # temp_display[6:0] $end
$var reg 1 $ a_c_on $end
$var reg 1 % furnace_on $end
$var reg 1 & display_select $end
$var reg 1 ' cool $end
$var reg 1 ( heat $end
$scope module uut $end
$var reg 7 ) current_temp[6:0] $end
$var reg 7 * desired_temp[6:0] $end
$var reg 1 + display_select $end
$var reg 1 , cool $end
$var reg 1 - heat $end
$var reg 1 . a_c_on $end
$var reg 1 / furnace_on $end
$var reg 7 0 temp_display[6:0] $end
$upscope $end
$upscope $end
$enddefinitions $end
#0
b0000000 !
b1111111 "
b1111111 #
0$
0%
0&
0'
0(
b0000000 )
b1111111 *
0+
0,
0-
0.
0/
b1111111 0
#10000000
b0000000 #
1&
1+
b0000000 0
#20000000
1%
1(
1-
1/
#30000000
b1111111 !
b0000000 "
b1111111 #
0%
b1111111 )
b0000000 *
0/
b1111111 0
#40000000
1$
1'
0(
1,
0-
1.
#50000000
#60000000
0$
0'
1(
0,
1-
0.
#70000000
b0000000 !
b1111111 "
b0000000 #
1%
b0000000 )
b1111111 *
1/
b0000000 0
#80000000
0%
1'
0(
1,
0-
0/
